backports/__init__.py
backports/zstd/__init__.py
backports/zstd/__init__.pyi
backports/zstd/_shutil.py
backports/zstd/_streams.py
backports/zstd/_zstd.cpython-313t-aarch64-linux-musl.so
backports/zstd/_zstd.py
backports/zstd/_zstdfile.py
backports/zstd/py.typed
backports/zstd/tarfile.py
backports/zstd/tarfile.pyi
backports/zstd/_cffi/__init__.py
backports/zstd/_cffi/_blocks_output_buffer.py
backports/zstd/_cffi/_common.py
backports/zstd/_cffi/buffer.py
backports/zstd/_cffi/compressor.py
backports/zstd/_cffi/decompressor.py
backports/zstd/_cffi/zstddict.py
backports/zstd/zipfile/__init__.py
backports/zstd/zipfile/__init__.pyi
backports/zstd/zipfile/__main__.py
backports/zstd/zipfile/_path/__init__.py
backports/zstd/zipfile/_path/__init__.pyi
backports/zstd/zipfile/_path/glob.py
backports/zstd/zipfile/_path/glob.pyi
backports_zstd-1.0.0.dist-info/METADATA
backports_zstd-1.0.0.dist-info/WHEEL
backports_zstd-1.0.0.dist-info/top_level.txt
backports_zstd-1.0.0.dist-info/RECORD
backports_zstd-1.0.0.dist-info/licenses/LICENSE.txt
backports_zstd-1.0.0.dist-info/licenses/LICENSE_zstd.txt
