Metadata-Version: 2.4
Name: backports.zstd
Version: 1.0.0
Summary: Backport of compression.zstd
Author-email: Rogdham <contact@rogdham.net>
License-Expression: PSF-2.0
Project-URL: Homepage, https://github.com/rogdham/backports.zstd
Project-URL: Source, https://github.com/rogdham/backports.zstd
Keywords: backport,backports,pep-784,zstd
Classifier: Development Status :: 5 - Production/Stable
Classifier: Intended Audience :: Developers
Classifier: Topic :: System :: Archiving :: Compression
Classifier: Programming Language :: Python
Classifier: Programming Language :: Python :: 3
Classifier: Programming Language :: Python :: 3 :: Only
Classifier: Programming Language :: Python :: 3.9
Classifier: Programming Language :: Python :: 3.10
Classifier: Programming Language :: Python :: 3.11
Classifier: Programming Language :: Python :: 3.12
Classifier: Programming Language :: Python :: 3.13
Requires-Python: <3.14,>=3.9
License-File: LICENSE.txt
License-File: LICENSE_zstd.txt
Dynamic: license-file
